{
  "topics": [
    {
      "title": "Bleeding, External",
      "state": "app.bleeding.bleedingExternal",
      "head": "Bleeding",
      "url": "/bleeding-external"
    },
    {
      "title": "Tourniquet to control bleeding",
      "state": "app.bleeding.controlBleedingUsingTourniquet",
      "head": "Bleeding",
      "url": "/control-bleeding-using-tourniquet"
    },
    {
      "title": "Bleeding, Internal",
      "state": "app.bleeding.bleedingInternal",
      "head": "Bleeding",
      "url": "/bleeding-internal"
    }
  ]
}